youtube_dlp_server/__init__.py
youtube_dlp_server/__main__.py
youtube_dlp_server/helper.py
youtube_dlp_server/server.py
youtube_dlp_server-0.1.0.dist-info/METADATA
youtube_dlp_server-0.1.0.dist-info/WHEEL
youtube_dlp_server-0.1.0.dist-info/entry_points.txt
youtube_dlp_server-0.1.0.dist-info/licenses/LICENSE
youtube_dlp_server-0.1.0.dist-info/RECORD
