Metadata-Version: 2.4
Name: youtube-dlp-server
Version: 0.1.0
Summary: Let your AI to view Youtube video, get info, subtitle and more. Even downloading.
Project-URL: Homepage, https://github.com/yourusername/youtube-dlp-server
Project-URL: Repository, https://github.com/yourusername/youtube-dlp-server
Project-URL: Documentation, https://github.com/yourusername/youtube-dlp-server#readme
Project-URL: Issues, https://github.com/yourusername/youtube-dlp-server/issues
Author-email: Robin <robin.xw@hotmail.com>
License: MIT
License-File: LICENSE
Keywords: ai,comments,dlp,mcp,subtitles,video,youtube
Classifier: Development Status :: 4 - Beta
Classifier: Intended Audience :: Developers
Classifier: License :: OSI Approved :: MIT License
Classifier: Programming Language :: Python :: 3
Classifier: Programming Language :: Python :: 3.11
Classifier: Programming Language :: Python :: 3.12
Classifier: Topic :: Internet :: WWW/HTTP
Classifier: Topic :: Multimedia :: Video
Classifier: Topic :: Software Development :: Libraries :: Python Modules
Requires-Python: >=3.11
Requires-Dist: mcp>=1.9.3
Requires-Dist: python-ffmpeg==2.0.12
Requires-Dist: requests>=2.31.0
Requires-Dist: yt-dlp==2025.5.22
